roc_tools
