Metadata-Version: 1.1
Name: roc-tools
Version: 0.3.0
Summary: Roc charting tools
Home-page: https://github.com/fengyu05/roc
Author: fengyu05
Author-email: fengyu05@gmail.com
License: MIT
Keywords: roc
Platform: UNKNOWN
Classifier: Development Status :: 3 - Alpha
Classifier: Intended Audience :: Developers
Classifier: Topic :: Software Development :: Build Tools
Classifier: License :: OSI Approved :: MIT License
Classifier: Programming Language :: Python :: 2.7
Classifier: Programming Language :: Python :: 3
Classifier: Programming Language :: Python :: 3.5
Classifier: Programming Language :: Python :: 3.6
Classifier: Programming Language :: Python :: 3.7
Classifier: Programming Language :: Python :: 3.8
